[{"Id":1,"Title":"1","Description":"1","IsCompleted":false,"CreatedAt":"2026-03-13T23:01:58.5347637+00:00","CompletedAt":null},{"Id":2,"Title":"1","Description":"1","IsCompleted":false,"CreatedAt":"2026-03-13T23:02:03.3094478+00:00","CompletedAt":null},{"Id":3,"Title":"1","Description":"1","IsCompleted":false,"CreatedAt":"2026-03-13T23:02:20.8616893+00:00","CompletedAt":null},{"Id":4,"Title":null,"Description":null,"IsCompleted":false,"CreatedAt":"2026-03-13T23:33:11.6369855+00:00","CompletedAt":null},{"Id":5,"Title":null,"Description":null,"IsCompleted":false,"CreatedAt":"2026-03-13T23:37:16.2791759+00:00","CompletedAt":null},{"Id":6,"Title":"helpme","Description":"dsads SDADSA","IsCompleted":false,"CreatedAt":"2026-03-13T23:41:41.0196199+00:00","CompletedAt":null}]